tb_gateway/__init__.py
tb_gateway/vw_gateway/__init__.py
tb_gateway/vw_gateway/main.py
tb_gateway/vw_gateway/requirements.txt
tb_gateway/vw_gateway/extensions/__init__.py
tb_gateway/vw_gateway/extensions/attendence/__init__.py
tb_gateway/vw_gateway/extensions/attendence/zktec/zktec_connector.py
tb_gateway/vw_gateway/extensions/printer/cups/cups_connector.py
tb_gateway/vw_gateway/templates/conf.json
tb_gateway/vw_gateway/templates/logs.json
tb_gateway/vw_gateway/templates/statistics.json
tb_gateway/vw_gateway/templates/devices/cups.json
tb_gateway/vw_gateway/templates/devices/zktec.json
tb_gateway/zkteco/__init__.py
tb_gateway/zkteco/cli.py
tb_gateway/zkteco/devices.py
tb_gateway-6.0.8.dist-info/licenses/LICENSE.txt
tb_gateway-6.0.8.dist-info/METADATA
tb_gateway-6.0.8.dist-info/WHEEL
tb_gateway-6.0.8.dist-info/entry_points.txt
tb_gateway-6.0.8.dist-info/top_level.txt
tb_gateway-6.0.8.dist-info/RECORD
