Metadata-Version: 2.4
Name: tb-gateway
Version: 6.0.8
Summary: Add a short description here!
Home-page: https://github.com/pyscaffold/pyscaffold/
Author: esmaeil-koohi
Author-email: esmaeil76koohi@gmail.com
License: MIT
Project-URL: Documentation, https://pyscaffold.org/
Platform: any
Classifier: Development Status :: 4 - Beta
Classifier: Programming Language :: Python
License-File: LICENSE.txt
Requires-Dist: importlib-metadata; python_version < "3.8"
Requires-Dist: tb-mqtt-client>=1.5
Requires-Dist: pyzk==0.9
Requires-Dist: pytz==2023.3
Requires-Dist: pyfiglet==0.8.post1
Requires-Dist: thingsboard-gateway==3.5.1
Requires-Dist: schema==0.7.5
Requires-Dist: protobuf==3.20
Requires-Dist: typer>=0.16.0
Provides-Extra: testing
Requires-Dist: setuptools; extra == "testing"
Requires-Dist: pytest; extra == "testing"
Requires-Dist: pytest-cov; extra == "testing"
Dynamic: license-file
